scripts/__init__.py
scripts/__main__.py
pig_manager-1.0.5.dist-info/METADATA
pig_manager-1.0.5.dist-info/WHEEL
pig_manager-1.0.5.dist-info/dependency_links.txt
pig_manager-1.0.5.dist-info/entry_points.txt
pig_manager-1.0.5.dist-info/top_level.txt
pig_manager-1.0.5.dist-info/RECORD
